simplecpreprocessor/__init__.py
simplecpreprocessor/__main__.py
simplecpreprocessor/core.py
simplecpreprocessor/exceptions.py
simplecpreprocessor/filesystem.py
simplecpreprocessor/platform.py
simplecpreprocessor/test_preprocessor.py
simplecpreprocessor/tokens.py
simplecpreprocessor/version.py
simplecpreprocessor-2.3.4.dist-info/entry_points.txt
simplecpreprocessor-2.3.4.dist-info/LICENSE.txt
simplecpreprocessor-2.3.4.dist-info/WHEEL
simplecpreprocessor-2.3.4.dist-info/METADATA
simplecpreprocessor-2.3.4.dist-info/RECORD
