Metadata-Version: 2.1
Name: simplecpreprocessor
Version: 2.3.4
Summary: simplepreprocessor expands limited set of C preprocessor macros
Author-email: Seppo Yli-Olli <seppo.yli-olli@iki.fi>
Requires-Python: >=3.7
Classifier: License :: OSI Approved :: MIT License
Requires-Dist: pytest>=3.6 ; extra == "test"
Requires-Dist: flake8 ; extra == "test"
Requires-Dist: pytest-cov ; extra == "test"
Requires-Dist: mock ; extra == "test"
Provides-Extra: test
